LICENSE
isortd/__init__.py
isortd/__main__.py
isortd/main.py
isortd-0.1.7.dist-info/LICENSE
isortd-0.1.7.dist-info/WHEEL
isortd-0.1.7.dist-info/METADATA
isortd-0.1.7.dist-info/RECORD
