Metadata-Version: 2.1
Name: isortd
Version: 0.1.7
Summary: isort daemon. Http api to isort
Home-page: https://github.com/urm8/isortd
License: WTFPL
Keywords: import,sort
Author: mm
Author-email: megafukz@gmail.com
Requires-Python: >=3.6.1,<4.0
Classifier: Environment :: Console
Classifier: Framework :: Flake8
Classifier: License :: Other/Proprietary License
Classifier: Operating System :: OS Independent
Classifier: Programming Language :: Python :: 3
Classifier: Programming Language :: Python :: 3.7
Classifier: Programming Language :: Python :: 3.8
Classifier: Programming Language :: Python :: 3.9
Classifier: Topic :: Software Development :: Documentation
Classifier: Topic :: Software Development :: Libraries :: Python Modules
Classifier: Topic :: Software Development :: Quality Assurance
Requires-Dist: aiohttp (>=3.7.0,<4.0.0)
Requires-Dist: aiohttp-cors (>=0.7.0,<0.8.0)
Requires-Dist: aiohttp_cors (>=0.7.0,<0.8.0)
Requires-Dist: click (>=7.1.2,<8.0.0)
Requires-Dist: isort (>=5,<6)
Project-URL: Repository, https://github.com/urm8/isortd
